<?xml version='1.0' encoding='UTF-8'?>
<package version="1.1.0" installOnlyAtStartup="false" uuid="evolution_game-2c85ec">
 <names>
  <name lang="de_DE">evolution game</name>
  <name lang="en_US">Karriereleiter_Auflockerungsspiel</name>
 </names>
 <descriptions>
  <description lang="de_DE">This game serves to loosen up the lesson a bit. It can be done with any number of students. ~15min</description>
 </descriptions>
 <supportedLanguages>
  <language>de_DE</language>
 </supportedLanguages>
 <descriptionLanguages>
  <language>de_DE</language>
 </descriptionLanguages>
 <contents>
  <behaviorContent path="behavior_1">
   <userRequestable/>
   <nature>interactive</nature>
   <names>
    <name lang="de_DE">evolution game</name>
   </names>
   <descriptions>
    <description lang="de_DE">A small evolution game to performe with students. It will take about 15 minutes.</description>
   </descriptions>
   <permissions>
    <canStandUp/>
    <canSitDown/>
   </permissions>
  </behaviorContent>
 </contents>
 <requirements>
  <naoqiRequirement minVersion="2.8" maxVersion="2.8"/>
  <robotRequirement model="NAO" minHeadVersion="5.0" maxHeadVersion="5.0" minBodyVersion="5.0" maxBodyVersion="5.0"/>
 </requirements>
</package>
